ADIASManager/ADIASManager.py
ADIASManager/__init__.py
ADIASManager-2023.10.5.dist-info/METADATA
ADIASManager-2023.10.5.dist-info/WHEEL
ADIASManager-2023.10.5.dist-info/top_level.txt
ADIASManager-2023.10.5.dist-info/RECORD
